cubicweb_iprogress/__init__.py
cubicweb_iprogress/__pkginfo__.py
cubicweb_iprogress/entities.py
cubicweb_iprogress/views.py
cubicweb_iprogress/data/cubes.iprogress.css
cubicweb_iprogress/data/cubes.iprogress.js
cubicweb_iprogress/i18n/de.po
cubicweb_iprogress/i18n/en.po
cubicweb_iprogress/i18n/es.po
cubicweb_iprogress/i18n/fr.po
cubicweb_iprogress-1.1.1.dist-info/METADATA
cubicweb_iprogress-1.1.1.dist-info/WHEEL
cubicweb_iprogress-1.1.1.dist-info/entry_points.txt
cubicweb_iprogress-1.1.1.dist-info/top_level.txt
cubicweb_iprogress-1.1.1.dist-info/RECORD
